LICENSE
README.md
setup.cfg
setup.py
synthemol/__init__.py
synthemol/_version.py
synthemol/constants.py
synthemol/py.typed
synthemol/utils.py
synthemol.egg-info/PKG-INFO
synthemol.egg-info/SOURCES.txt
synthemol.egg-info/dependency_links.txt
synthemol.egg-info/entry_points.txt
synthemol.egg-info/requires.txt
synthemol.egg-info/top_level.txt
synthemol/generate/__init__.py
synthemol/generate/generate.py
synthemol/generate/generator.py
synthemol/generate/node.py
synthemol/generate/utils.py
synthemol/models/__init__.py
synthemol/models/chemprop_models.py
synthemol/models/sklearn_models.py
synthemol/reactions/__init__.py
synthemol/reactions/custom.py
synthemol/reactions/query_mol.py
synthemol/reactions/reaction.py
synthemol/reactions/real.py
synthemol/reactions/utils.py
synthemol/resources/real/building_blocks.csv
synthemol/resources/real/reaction_to_building_blocks.pkl