Metadata-Version: 2.1
Name: synthemol
Version: 1.0.0
Summary: synthemol
Home-page: https://github.com/swansonk14/SyntheMol
Download-URL: https://github.com/swansonk14/SyntheMol/archive/refs/tags/v_1.0.0.tar.gz
Author: Kyle Swanson
Author-email: swansonk.14@gmail.com
License: MIT
Keywords: machine learning,drug design,generative models,synthesizable molecules
Classifier: Programming Language :: Python :: 3
Classifier: Programming Language :: Python :: 3.10
Classifier: Programming Language :: Python :: 3.11
Classifier: Programming Language :: Python :: 3.12
Classifier: License :: OSI Approved :: MIT License
Classifier: Operating System :: OS Independent
Classifier: Typing :: Typed
Requires-Python: >=3.10
License-File: LICENSE
